pg_sql/__init__.py
pg_sql/version.py
pgsql/__init__.py
pgsql/version.py
pg_sql-0.0.1.dist-info/LICENSE.txt
pg_sql-0.0.1.dist-info/METADATA
pg_sql-0.0.1.dist-info/WHEEL
pg_sql-0.0.1.dist-info/top_level.txt
pg_sql-0.0.1.dist-info/RECORD
